svrprompt/__init__.py
svrprompt/__main__.py
svrprompt/cli.py
svrprompt/constants.py
svrprompt/cookies.py
svrprompt/debug.py
svrprompt/errors.py
svrprompt/models.py
svrprompt/typing.py
svrprompt/version.py
svrprompt/Provider/ARTA.py
svrprompt/Provider/Blackbox.py
svrprompt/Provider/ChatGLM.py
svrprompt/Provider/ChatGpt.py
svrprompt/Provider/Chatai.py
svrprompt/Provider/Cloudflare.py
svrprompt/Provider/Copilot.py
svrprompt/Provider/DDG.py
svrprompt/Provider/DeepInfraChat.py
svrprompt/Provider/DocsBot.py
svrprompt/Provider/DuckDuckGo.py
svrprompt/Provider/Dynaspark.py
svrprompt/Provider/Free2GPT.py
svrprompt/Provider/FreeGpt.py
svrprompt/Provider/GizAI.py
svrprompt/Provider/ImageLabs.py
svrprompt/Provider/LMArenaProvider.py
svrprompt/Provider/LambdaChat.py
svrprompt/Provider/Liaobots.py
svrprompt/Provider/OIVSCodeSer0501.py
svrprompt/Provider/OIVSCodeSer2.py
svrprompt/Provider/OIVSCodeSer5.py
svrprompt/Provider/PerplexityLabs.py
svrprompt/Provider/Pi.py
svrprompt/Provider/Pizzagpt.py
svrprompt/Provider/PollinationsAI.py
svrprompt/Provider/PollinationsImage.py
svrprompt/Provider/PuterJS.py
svrprompt/Provider/SearXNG.py
svrprompt/Provider/TeachAnything.py
svrprompt/Provider/WeWordle.py
svrprompt/Provider/Websim.py
svrprompt/Provider/You.py
svrprompt/Provider/Yqcloud.py
svrprompt/Provider/__init__.py
svrprompt/Provider/base_provider.py
svrprompt/Provider/helper.py
svrprompt/Provider/__pycache__/ARTA.cpython-311.pyc
svrprompt/Provider/__pycache__/Blackbox.cpython-311.pyc
svrprompt/Provider/__pycache__/ChatGLM.cpython-311.pyc
svrprompt/Provider/__pycache__/ChatGpt.cpython-311.pyc
svrprompt/Provider/__pycache__/Chatai.cpython-311.pyc
svrprompt/Provider/__pycache__/Cloudflare.cpython-311.pyc
svrprompt/Provider/__pycache__/Copilot.cpython-311.pyc
svrprompt/Provider/__pycache__/DDG.cpython-311.pyc
svrprompt/Provider/__pycache__/DeepInfraChat.cpython-311.pyc
svrprompt/Provider/__pycache__/DocsBot.cpython-311.pyc
svrprompt/Provider/__pycache__/DuckDuckGo.cpython-311.pyc
svrprompt-1.4.dist-info/METADATA
svrprompt-1.4.dist-info/WHEEL
svrprompt-1.4.dist-info/top_level.txt
svrprompt-1.4.dist-info/RECORD
