Metadata-Version: 2.1
Name: svrprompt
Version: 1.4
Summary: svrprompt
Author: afkdev
Author-email: afk256rec@gmail.com
Classifier: Programming Language :: Python :: 3
Classifier: License :: OSI Approved :: MIT License
Classifier: Operating System :: OS Independent
Requires-Python: >=3.9
